{
  "hash": "c6f4430d",
  "configHash": "37f8c53c",
  "lockfileHash": "6e87da37",
  "browserHash": "4be91bd5",
  "optimized": {
    "vue": {
      "src": "../../../../node_modules/vue/dist/vue.runtime.esm-bundler.js",
      "file": "vue.js",
      "fileHash": "8566b92f",
      "needsInterop": false
    },
    "vitepress > @vue/devtools-api": {
      "src": "../../../../node_modules/@vue/devtools-api/dist/index.js",
      "file": "vitepress___@vue_devtools-api.js",
      "fileHash": "3536c669",
      "needsInterop": false
    },
    "vitepress > @vueuse/core": {
      "src": "../../../../node_modules/@vueuse/core/index.mjs",
      "file": "vitepress___@vueuse_core.js",
      "fileHash": "a0d02cad",
      "needsInterop": false
    },
    "vitepress > @vueuse/integrations/useFocusTrap": {
      "src": "../../../../node_modules/@vueuse/integrations/useFocusTrap.mjs",
      "file": "vitepress___@vueuse_integrations_useFocusTrap.js",
      "fileHash": "a027ac97",
      "needsInterop": false
    },
    "vitepress > mark.js/src/vanilla.js": {
      "src": "../../../../node_modules/mark.js/src/vanilla.js",
      "file": "vitepress___mark__js_src_vanilla__js.js",
      "fileHash": "7c952ef4",
      "needsInterop": false
    },
    "vitepress > minisearch": {
      "src": "../../../../node_modules/minisearch/dist/es/index.js",
      "file": "vitepress___minisearch.js",
      "fileHash": "30d2eaec",
      "needsInterop": false
    }
  },
  "chunks": {
    "chunk-KNUCHIUH": {
      "file": "chunk-KNUCHIUH.js"
    },
    "chunk-URVHZSMY": {
      "file": "chunk-URVHZSMY.js"
    }
  }
}